{
  "##choices#calibration_time": 10.0, 
  "##choices#cmd_key": "encode", 
  "##choices#compile_type": "dynamic", 
  "##choices#compiler_description_uoa": "gcc-4.9.0-auto", 
  "##choices#compiler_flags#base_opt": "-O1", 
  "##choices#compiler_flags#bool--fira-region=": "-fira-region=one", 
  "##choices#compiler_flags#bool-compare-elim": "-fcompare-elim", 
  "##choices#compiler_flags#bool-defer-pop": "-fno-defer-pop", 
  "##choices#compiler_flags#bool-inline-functions-called-once": "-fno-inline-functions-called-once", 
  "##choices#compiler_flags#bool-loop-block": "-floop-block", 
  "##choices#compiler_flags#bool-ree": "-free", 
  "##choices#compiler_flags#bool-sched-last-insn-heuristic": "-fno-sched-last-insn-heuristic", 
  "##choices#compiler_flags#bool-sched-rank-heuristic": "-fno-sched-rank-heuristic", 
  "##choices#compiler_flags#bool-sched-spec-load": "-fsched-spec-load", 
  "##choices#compiler_flags#bool-section-anchors": "-fsection-anchors", 
  "##choices#compiler_flags#bool-signaling-nans": "-fsignaling-nans", 
  "##choices#compiler_flags#bool-trapping-math": "-fno-trapping-math", 
  "##choices#compiler_flags#bool-tree-bit-ccp": "-ftree-bit-ccp", 
  "##choices#compiler_flags#bool-tree-copy-prop": "-fno-tree-copy-prop", 
  "##choices#compiler_flags#bool-tree-dominator-opts": "-ftree-dominator-opts", 
  "##choices#compiler_flags#bool-tree-loop-im": "-ftree-loop-im", 
  "##choices#compiler_flags#bool-variable-expansion-in-unroller": "-fvariable-expansion-in-unroller", 
  "##choices#compiler_flags#bool-vpt": "-fno-vpt", 
  "##choices#compiler_flags#bool-wpa": "-fno-wpa", 
  "##choices#compiler_flags#param-asan-memintrin": "--param asan-memintrin=1", 
  "##choices#compiler_flags#param-ipa-sra-ptr-growth-factor": "--param ipa-sra-ptr-growth-factor=1", 
  "##choices#compiler_flags#param-ipcp-unit-growth": "--param ipcp-unit-growth=9", 
  "##choices#compiler_flags#param-max-fields-for-field-sensitive": "--param max-fields-for-field-sensitive=0", 
  "##choices#compiler_flags#param-min-size-for-stack-sharing": "--param min-size-for-stack-sharing=9", 
  "##choices#compiler_flags#param-sms-max-ii-factor": "--param sms-max-ii-factor=141", 
  "##choices#compiler_flags#param-switch-conversion-max-branch-ratio": "--param switch-conversion-max-branch-ratio=9", 
  "##choices#compiler_flags#param-tracer-min-branch-probability-feedback": "--param tracer-min-branch-probability-feedback=68", 
  "##choices#data_uoa": "zlib", 
  "##choices#dataset_file": "data.y4m", 
  "##choices#dataset_uoa": "video-raw-0001", 
  "##choices#device_id": "", 
  "##choices#host_os": "linux-32", 
  "##choices#module_uoa": "b0ac08fe1d3c2615", 
  "##choices#no_state_check": "yes", 
  "##choices#program_tags": "", 
  "##choices#repeat": 10, 
  "##choices#target": "", 
  "##choices#target_os": "linux-32", 
  "##choices#target_os_bits": "32"
}
