{
  "##choices#calibration_time": 10.0, 
  "##choices#cmd_key": "encode", 
  "##choices#compile_type": "dynamic", 
  "##choices#compiler_description_uoa": "gcc-4.9.0-auto", 
  "##choices#compiler_flags#base_opt": "-O0", 
  "##choices#compiler_flags#bool-crossjumping": "-fno-crossjumping", 
  "##choices#compiler_flags#bool-delete-null-pointer-checks": "-fno-delete-null-pointer-checks", 
  "##choices#compiler_flags#bool-fat-lto-objects": "-fno-fat-lto-objects", 
  "##choices#compiler_flags#bool-forward-propagate": "-fno-forward-propagate", 
  "##choices#compiler_flags#bool-function-sections": "-ffunction-sections", 
  "##choices#compiler_flags#bool-hoist-adjacent-loads": "-fhoist-adjacent-loads", 
  "##choices#compiler_flags#bool-ipa-cp": "-fipa-cp", 
  "##choices#compiler_flags#bool-ipa-pure-const": "-fno-ipa-pure-const", 
  "##choices#compiler_flags#bool-ira-share-spill-slots": "-fira-share-spill-slots", 
  "##choices#compiler_flags#bool-isolate-erroneous-paths-dereference": "-fisolate-erroneous-paths-dereference", 
  "##choices#compiler_flags#bool-keep-inline-functions": "-fno-keep-inline-functions", 
  "##choices#compiler_flags#bool-keep-static-consts": "-fkeep-static-consts", 
  "##choices#compiler_flags#bool-loop-nest-optimize": "-floop-nest-optimize", 
  "##choices#compiler_flags#bool-modulo-sched": "-fno-modulo-sched", 
  "##choices#compiler_flags#bool-predictive-commoning": "-fno-predictive-commoning", 
  "##choices#compiler_flags#bool-sched-last-insn-heuristic": "-fsched-last-insn-heuristic", 
  "##choices#compiler_flags#bool-schedule-insns2": "-fno-schedule-insns2", 
  "##choices#compiler_flags#bool-strict-aliasing": "-fno-strict-aliasing", 
  "##choices#compiler_flags#bool-tree-ch": "-fno-tree-ch", 
  "##choices#compiler_flags#bool-tree-sra": "-ftree-sra", 
  "##choices#data_uoa": "zlib", 
  "##choices#dataset_file": "data.y4m", 
  "##choices#dataset_uoa": "video-raw-0001", 
  "##choices#device_id": "", 
  "##choices#host_os": "linux-32", 
  "##choices#module_uoa": "b0ac08fe1d3c2615", 
  "##choices#no_state_check": "yes", 
  "##choices#program_tags": "", 
  "##choices#repeat": 10, 
  "##choices#target": "", 
  "##choices#target_os": "linux-32", 
  "##choices#target_os_bits": "32"
}
