{
  "control": [
    {
      "engine": "CK", 
      "iso_datetime": "2017-07-21T18:57:43.450568", 
      "version": [
        "1", 
        "9", 
        "1"
      ]
    }, 
    {
      "engine": "CK", 
      "iso_datetime": "2017-07-21T19:00:53.970030", 
      "version": [
        "1", 
        "9", 
        "1"
      ]
    }, 
    {
      "engine": "CK", 
      "iso_datetime": "2017-07-21T19:03:38.587042", 
      "version": [
        "1", 
        "9", 
        "1"
      ]
    }, 
    {
      "engine": "CK", 
      "iso_datetime": "2017-07-21T19:06:31.259781", 
      "version": [
        "1", 
        "9", 
        "1"
      ]
    }, 
    {
      "engine": "CK", 
      "iso_datetime": "2017-07-21T19:09:13.410141", 
      "version": [
        "1", 
        "9", 
        "1"
      ]
    }, 
    {
      "engine": "CK", 
      "iso_datetime": "2017-07-21T19:12:09.453479", 
      "version": [
        "1", 
        "9", 
        "1"
      ]
    }, 
    {
      "engine": "CK", 
      "iso_datetime": "2017-07-21T19:15:27.711999", 
      "version": [
        "1", 
        "9", 
        "1"
      ]
    }, 
    {
      "engine": "CK", 
      "iso_datetime": "2017-07-21T19:18:05.585260", 
      "version": [
        "1", 
        "9", 
        "1"
      ]
    }, 
    {
      "engine": "CK", 
      "iso_datetime": "2017-07-21T19:21:17.290479", 
      "version": [
        "1", 
        "9", 
        "1"
      ]
    }, 
    {
      "engine": "CK", 
      "iso_datetime": "2017-07-21T19:24:43.353408", 
      "version": [
        "1", 
        "9", 
        "1"
      ]
    }, 
    {
      "engine": "CK", 
      "iso_datetime": "2017-07-21T19:27:48.561073", 
      "version": [
        "1", 
        "9", 
        "1"
      ]
    }, 
    {
      "engine": "CK", 
      "iso_datetime": "2017-07-21T19:30:52.620847", 
      "version": [
        "1", 
        "9", 
        "1"
      ]
    }, 
    {
      "engine": "CK", 
      "iso_datetime": "2017-07-21T19:33:54.140544", 
      "version": [
        "1", 
        "9", 
        "1"
      ]
    }, 
    {
      "engine": "CK", 
      "iso_datetime": "2017-07-21T19:36:40.943380", 
      "version": [
        "1", 
        "9", 
        "1"
      ]
    }, 
    {
      "engine": "CK", 
      "iso_datetime": "2017-07-21T19:39:25.781068", 
      "version": [
        "1", 
        "9", 
        "1"
      ]
    }, 
    {
      "engine": "CK", 
      "iso_datetime": "2017-07-21T19:42:12.686373", 
      "version": [
        "1", 
        "9", 
        "1"
      ]
    }, 
    {
      "engine": "CK", 
      "iso_datetime": "2017-07-21T19:46:21.304416", 
      "version": [
        "1", 
        "9", 
        "1"
      ]
    }, 
    {
      "engine": "CK", 
      "iso_datetime": "2017-07-21T19:49:11.762839", 
      "version": [
        "1", 
        "9", 
        "1"
      ]
    }, 
    {
      "engine": "CK", 
      "iso_datetime": "2017-07-21T19:52:01.791752", 
      "version": [
        "1", 
        "9", 
        "1"
      ]
    }, 
    {
      "engine": "CK", 
      "iso_datetime": "2017-07-21T19:55:03.524122", 
      "version": [
        "1", 
        "9", 
        "1"
      ]
    }, 
    {
      "engine": "CK", 
      "iso_datetime": "2017-07-21T19:58:30.358957", 
      "version": [
        "1", 
        "9", 
        "1"
      ]
    }, 
    {
      "engine": "CK", 
      "iso_datetime": "2017-07-21T20:01:26.708298", 
      "version": [
        "1", 
        "9", 
        "1"
      ]
    }, 
    {
      "engine": "CK", 
      "iso_datetime": "2017-07-21T20:04:36.374594", 
      "version": [
        "1", 
        "9", 
        "1"
      ]
    }
  ]
}
