{
  "##choices#calibration_time": 10.0, 
  "##choices#cmd_key": "encode", 
  "##choices#compile_type": "dynamic", 
  "##choices#compiler_description_uoa": "gcc-7.1.0-auto", 
  "##choices#compiler_flags#base_opt": "-O3", 
  "##choices#compiler_flags#bool--fexcess-precision=": "-fexcess-precision=fast", 
  "##choices#compiler_flags#bool-expensive-optimizations": "-fno-expensive-optimizations", 
  "##choices#compiler_flags#bool-gcse-after-reload": "-fno-gcse-after-reload", 
  "##choices#compiler_flags#bool-ira-loop-pressure": "-fno-ira-loop-pressure", 
  "##choices#compiler_flags#bool-ira-share-save-slots": "-fno-ira-share-save-slots", 
  "##choices#compiler_flags#bool-loop-interchange": "-fno-loop-interchange", 
  "##choices#compiler_flags#bool-loop-strip-mine": "-fno-loop-strip-mine", 
  "##choices#compiler_flags#bool-peephole": "-fpeephole", 
  "##choices#compiler_flags#bool-peephole2": "-fpeephole2", 
  "##choices#compiler_flags#bool-reciprocal-math": "-freciprocal-math", 
  "##choices#compiler_flags#bool-sched-group-heuristic": "-fno-sched-group-heuristic", 
  "##choices#compiler_flags#bool-sel-sched-pipelining-outer-loops": "-fsel-sched-pipelining-outer-loops", 
  "##choices#compiler_flags#bool-shrink-wrap": "-fshrink-wrap", 
  "##choices#compiler_flags#bool-stdarg-opt": "-fstdarg-opt", 
  "##choices#compiler_flags#bool-strict-aliasing": "-fstrict-aliasing", 
  "##choices#compiler_flags#bool-thread-jumps": "-fthread-jumps", 
  "##choices#compiler_flags#bool-tree-slsr": "-fno-tree-slsr", 
  "##choices#compiler_flags#param--falign-jumps": "-falign-jumps=0", 
  "##choices#compiler_flags#param--falign-loops": "-falign-loops=0", 
  "##choices#compiler_flags#param--ftree-parallelize-loops=": "-ftree-parallelize-loops=0", 
  "##choices#compiler_flags#param-asan-globals": "--param asan-globals=0", 
  "##choices#compiler_flags#param-gcse-after-reload-critical-fraction": "--param gcse-after-reload-critical-fraction=17", 
  "##choices#compiler_flags#param-graphite-max-nb-scop-params": "--param graphite-max-nb-scop-params=3", 
  "##choices#compiler_flags#param-inline-min-speedup": "--param inline-min-speedup=17", 
  "##choices#compiler_flags#param-ipa-cp-value-list-size": "--param ipa-cp-value-list-size=1", 
  "##choices#compiler_flags#param-l1-cache-size": "--param l1-cache-size=47", 
  "##choices#compiler_flags#param-large-function-growth": "--param large-function-growth=185", 
  "##choices#compiler_flags#param-large-function-insns": "--param large-function-insns=4511", 
  "##choices#compiler_flags#param-loop-invariant-max-bbs-in-loop": "--param loop-invariant-max-bbs-in-loop=1200", 
  "##choices#compiler_flags#param-lto-min-partition": "--param lto-min-partition=1644", 
  "##choices#compiler_flags#param-max-cse-insns": "--param max-cse-insns=1061", 
  "##choices#compiler_flags#param-max-fsm-thread-length": "--param max-fsm-thread-length=169759", 
  "##choices#compiler_flags#param-max-gcse-insertion-ratio": "--param max-gcse-insertion-ratio=22", 
  "##choices#compiler_flags#param-max-inline-recursive-depth-auto": "--param max-inline-recursive-depth-auto=15", 
  "##choices#compiler_flags#param-max-iterations-to-track": "--param max-iterations-to-track=1186", 
  "##choices#compiler_flags#param-max-last-value-rtl": "--param max-last-value-rtl=4753", 
  "##choices#compiler_flags#param-max-stores-to-sink": "--param max-stores-to-sink=1", 
  "##choices#compiler_flags#param-max-vartrack-reverse-op-size": "--param max-vartrack-reverse-op-size=55", 
  "##choices#compiler_flags#param-max-vartrack-size": "--param max-vartrack-size=84379460", 
  "##choices#compiler_flags#param-sched-spec-prob-cutoff": "--param sched-spec-prob-cutoff=85", 
  "##choices#data_uoa": "zlib", 
  "##choices#dataset_file": "data.y4m", 
  "##choices#dataset_uoa": "video-raw-0001", 
  "##choices#device_id": "", 
  "##choices#host_os": "linux-32", 
  "##choices#module_uoa": "b0ac08fe1d3c2615", 
  "##choices#no_state_check": "yes", 
  "##choices#program_tags": "", 
  "##choices#repeat": 10, 
  "##choices#target": "", 
  "##choices#target_os": "linux-32", 
  "##choices#target_os_bits": "32"
}
