{
  "##choices#calibration_time": 10.0, 
  "##choices#cmd_key": "encode", 
  "##choices#compile_type": "dynamic", 
  "##choices#compiler_description_uoa": "gcc-7.1.0-auto", 
  "##choices#compiler_flags#base_opt": "-Ofast", 
  "##choices#compiler_flags#bool-expensive-optimizations": "-fno-expensive-optimizations", 
  "##choices#compiler_flags#bool-fast-math": "-ffast-math", 
  "##choices#compiler_flags#bool-gcse-lm": "-fgcse-lm", 
  "##choices#compiler_flags#bool-ipa-pta": "-fno-ipa-pta", 
  "##choices#compiler_flags#bool-ipa-pure-const": "-fipa-pure-const", 
  "##choices#compiler_flags#bool-ipa-ra": "-fipa-ra", 
  "##choices#compiler_flags#bool-ira-share-save-slots": "-fno-ira-share-save-slots", 
  "##choices#compiler_flags#bool-live-range-shrinkage": "-fno-live-range-shrinkage", 
  "##choices#compiler_flags#bool-lra-remat": "-flra-remat", 
  "##choices#compiler_flags#bool-reorder-blocks": "-fno-reorder-blocks", 
  "##choices#compiler_flags#bool-single-precision-constant": "-fno-single-precision-constant", 
  "##choices#compiler_flags#bool-toplevel-reorder": "-fno-toplevel-reorder", 
  "##choices#compiler_flags#bool-tree-coalesce-vars": "-fno-tree-coalesce-vars", 
  "##choices#compiler_flags#bool-tree-dse": "-fno-tree-dse", 
  "##choices#compiler_flags#bool-unsafe-loop-optimizations": "-fno-unsafe-loop-optimizations", 
  "##choices#compiler_flags#bool-wpa": "-fno-wpa", 
  "##choices#compiler_flags#param-asan-globals": "--param asan-globals=0", 
  "##choices#compiler_flags#param-cxx-max-namespaces-for-diagnostic-help": "--param cxx-max-namespaces-for-diagnostic-help=1711", 
  "##choices#compiler_flags#param-early-inlining-insns": "--param early-inlining-insns=7", 
  "##choices#compiler_flags#param-gcse-after-reload-partial-fraction": "--param gcse-after-reload-partial-fraction=1", 
  "##choices#compiler_flags#param-integer-share-limit": "--param integer-share-limit=185", 
  "##choices#compiler_flags#param-ipa-cp-array-index-hint-bonus": "--param ipa-cp-array-index-hint-bonus=30", 
  "##choices#compiler_flags#param-ipa-max-agg-items": "--param ipa-max-agg-items=5", 
  "##choices#compiler_flags#param-max-cse-insns": "--param max-cse-insns=728", 
  "##choices#compiler_flags#param-max-dse-active-local-stores": "--param max-dse-active-local-stores=1735", 
  "##choices#compiler_flags#param-max-pipeline-region-insns": "--param max-pipeline-region-insns=118", 
  "##choices#compiler_flags#param-max-sched-region-blocks": "--param max-sched-region-blocks=16", 
  "##choices#compiler_flags#param-max-slsr-cand-scan": "--param max-slsr-cand-scan=384239", 
  "##choices#compiler_flags#param-max-tail-merge-iterations": "--param max-tail-merge-iterations=0", 
  "##choices#compiler_flags#param-min-inline-recursive-probability": "--param min-inline-recursive-probability=7", 
  "##choices#compiler_flags#param-min-spec-prob": "--param min-spec-prob=12", 
  "##choices#compiler_flags#param-scev-max-expr-complexity": "--param scev-max-expr-complexity=19", 
  "##choices#data_uoa": "zlib", 
  "##choices#dataset_file": "data.y4m", 
  "##choices#dataset_uoa": "video-raw-0001", 
  "##choices#device_id": "", 
  "##choices#host_os": "linux-32", 
  "##choices#module_uoa": "b0ac08fe1d3c2615", 
  "##choices#no_state_check": "yes", 
  "##choices#program_tags": "", 
  "##choices#repeat": 10, 
  "##choices#target": "", 
  "##choices#target_os": "linux-32", 
  "##choices#target_os_bits": "32"
}
